Metadata-Version: 2.1
Name: EGETools
Version: 1.11
Summary: Library of functions for Russian Computer Science exams
Home-page: UNKNOWN
Author-email: mhdtadev@gmail.com
License: UNKNOWN
Platform: UNKNOWN
